ttss/ColorType.py
ttss/Mode.py
ttss/Passage.py
ttss/Path.py
ttss/PositionType.py
ttss/Route.py
ttss/Status.py
ttss/Stop.py
ttss/StopPoint.py
ttss/TTSS.py
ttss/Trip.py
ttss/Vehicle.py
ttss/__init__.py
ttss/extractors.py
ttss/py.typed
ttss/utils.py
ttss-0.8.0.dist-info/LICENSE
ttss-0.8.0.dist-info/METADATA
ttss-0.8.0.dist-info/WHEEL
ttss-0.8.0.dist-info/top_level.txt
ttss-0.8.0.dist-info/RECORD
