Metadata-Version: 2.1
Name: ttss
Version: 0.8.0
Summary: A Python wrapper for TTSS API.
Home-page: https://github.com/tomekzaw/ttss
Author: Tomek Zawadzki
Author-email: tomekzawadzki98@gmail.com
Project-URL: Bug Tracker, https://github.com/tomekzaw/ttss/issues
Classifier: Programming Language :: Python :: 3
Classifier: License :: OSI Approved :: MIT License
Classifier: Operating System :: OS Independent
Requires-Python: >=3.8
License-File: LICENSE
Requires-Dist: requests
Requires-Dist: pytz
